mmt/__init__.py
mmt/exceptions.py
mmt/file.py
mmt/version.py
mmt/commands/__init__.py
mmt/commands/branch.py
mmt/commands/checkout.py
mmt/commands/config.py
mmt/commands/credential.py
mmt/commands/diff.py
mmt/commands/info.py
mmt/commands/log.py
mmt/commands/pull.py
mmt/commands/push.py
mmt/commands/remote.py
mmt/commands/revert.py
mmt/commands/sri.py
mmt/commands/status.py
mmt/commands/switch.py
mmt/commands/tag.py
mmt/managers/__init__.py
mmt/managers/config.py
mmt/managers/credential.py
mmt/managers/remote.py
mmt/managers/setting.py
mmt/metadata/__init__.py
mmt/metadata/config.py
mmt/metadata/globalconfig.py
mmt/metadata/localconfig.py
mmt/metadata/state.py
test/__init__.py
test/main.py
test/test_PS.py
test/test_branch.py
test/test_checkout.py
test/test_config.py
test/test_credential.py
test/test_diff.py
test/test_info.py
test/test_log.py
test/test_other.py
test/test_pull.py
test/test_push.py
test/test_regression_MMT_67.py
test/test_regression_MMT_68.py
test/test_regression_MMT_69.py
test/test_regression_MMT_72.py
test/test_regression_MMT_80.py
test/test_remote.py
test/test_revert.py
test/test_sri.py
test/test_standalone.py
test/test_status.py
test/test_switch.py
test/test_tag.py
miva_mmt-1.0.6.dist-info/LICENSE
miva_mmt-1.0.6.dist-info/METADATA
miva_mmt-1.0.6.dist-info/WHEEL
miva_mmt-1.0.6.dist-info/entry_points.txt
miva_mmt-1.0.6.dist-info/top_level.txt
miva_mmt-1.0.6.dist-info/RECORD
