Metadata-Version: 2.1
Name: miva-mmt
Version: 1.0.6
Summary: Miva Managed Templates (MMT)
Home-page: https://docs.miva.com/template-branches/template-branches-overview#mmt_overview
Author: Miva, Inc.
Author-email: support@miva.com
License: MMT License Agreement
Platform: UNKNOWN
Requires-Python: >=3.6
Requires-Dist: merchantapi (>=2.7.0)
